gazelib/__init__.py
gazelib/containers.py
gazelib/io.py
gazelib/package.py
gazelib/settings.py
gazelib/validation.py
gazelib/conversion/__init__.py
gazelib/conversion/utils.py
gazelib/conversion/icl/__init__.py
gazelib/conversion/icl/cg/__init__.py
gazelib/conversion/icl/cg/common.py
gazelib/conversion/icl/gazelibfixtures/__init__.py
gazelib/conversion/icl/gazelibfixtures/common.py
gazelib/legacy/__init__.py
gazelib/legacy/igazelib.py
gazelib/models/__init__.py
gazelib/models/fixation.py
gazelib/models/saccade.py
gazelib/preprocessing/__init__.py
gazelib/statistics/__init__.py
gazelib/statistics/utils.py
gazelib/visualization/__init__.py
gazelib/visualization/common.py
gazelib/visualization/utils.py
gazelib/visualization/templates/overview.html
gazelib-2.1.1.dist-info/DESCRIPTION.rst
gazelib-2.1.1.dist-info/METADATA
gazelib-2.1.1.dist-info/RECORD
gazelib-2.1.1.dist-info/WHEEL
gazelib-2.1.1.dist-info/metadata.json
gazelib-2.1.1.dist-info/top_level.txt
