Metadata-Version: 2.0
Name: gazelib
Version: 2.1.1
Summary: Software tools to manage and analyze data from eye-trackers
Home-page: https://github.com/infant-cognition-tampere/gazelib
Author: Akseli Palen
Author-email: akseli.palen@gmail.com
License: GPLv3
Keywords: eye-tracking data
Platform: UNKNOWN
Classifier: Development Status :: 4 - Beta
Classifier: Intended Audience :: Developers
Classifier: Intended Audience :: Science/Research
Classifier: Topic :: Scientific/Engineering :: Bio-Informatics
Classifier: Topic :: Scientific/Engineering :: Image Recognition
Classifier: Topic :: Scientific/Engineering :: Human Machine Interfaces
Classifier: Topic :: Scientific/Engineering :: Information Analysis
Classifier: License :: OSI Approved :: GNU General Public License v3 (GPLv3)
Classifier: Programming Language :: Python :: 2
Classifier: Programming Language :: Python :: 3
Classifier: Operating System :: OS Independent
Requires-Dist: bokeh
Requires-Dist: deepdiff
Requires-Dist: fixationmodel
Requires-Dist: jsonschema
Requires-Dist: numpy
Requires-Dist: saccademodel
Requires-Dist: scipy
Requires-Dist: six
Provides-Extra: dev
Requires-Dist: Sphinx; extra == 'dev'
Requires-Dist: six; extra == 'dev'
